entities/AdminAuthInformation.py
entities/ClientInformation.py
entities/EmCarsDailyInformation.py
entities/EmCarsDailyRpt.py
entities/InsuranceInformation.py
entities/LastRunDate.py
entities/StickerInformation.py
entities/UserAuthInformation.py
entities/VehicleInformation.py
entities/__init__.py
methods/__init__.py
methods/em4datastore.py
em4_datastore_py3-0.0.4.dist-info/METADATA
em4_datastore_py3-0.0.4.dist-info/WHEEL
em4_datastore_py3-0.0.4.dist-info/top_level.txt
em4_datastore_py3-0.0.4.dist-info/RECORD
