Metadata-Version: 2.1
Name: em4-datastore-py3
Version: 0.0.4
Summary: A google cloud datastore package for em4 projects
Home-page: https://github.com/4-0-analytics/em4-datastore-py3
Author: Steve H.
Author-email: hwuang@aim.com
License: MIT
Project-URL: Bug Tracker, https://github.com/4-0-analytics/em4-datastore-py3/issues
Keywords: example project
Platform: UNKNOWN
Classifier: Programming Language :: Python :: 3
Classifier: License :: OSI Approved :: MIT License
Classifier: Operating System :: OS Independent
Requires-Python: >=3.6
